wunderground
