Metadata-Version: 1.0
Name: django-wunderground
Version: 1.0.1
Summary: An extension for Django CMS and a template tag that displays the current local weather pulled from  wunderground.com
Home-page: http://github.com/powellc/django-wunderground
Author: Mark Ransom, Colin Powell
Author-email: megamark16@gmail.com, colin.powell@gmail.com
License: BSD
Platform: OS Independent
Classifier: Development Status :: 4 - Beta
Classifier: Framework :: Django
Classifier: Intended Audience :: Developers
Classifier: License :: OSI Approved :: BSD License
Classifier: Operating System :: OS Independent
Classifier: Programming Language :: Python
Classifier: Topic :: Internet :: WWW/HTTP
Classifier: Topic :: Internet :: WWW/HTTP :: Dynamic Content
